Metadata-Version: 2.1
Name: bph-pal
Version: 0.1.1
Summary: Protocol abstraction and parser for BPH
Home-page: https://github.com/riot-appstore/BPH
Author: Kevin Weiss
Author-email: weiss.kevin604@gmail.com
License: MIT
Platform: any
Classifier: Programming Language :: Python :: 3
Classifier: License :: OSI Approved :: MIT License
Classifier: Operating System :: OS Independent
Classifier: Development Status :: 2 - Pre-Alpha
Classifier: Intended Audience :: Developers
Requires-Python: >=3.4.*
